SNgramExtractor.py
SNgramExtractor-0.0.6.dist-info/LICENSE
SNgramExtractor-0.0.6.dist-info/METADATA
SNgramExtractor-0.0.6.dist-info/WHEEL
SNgramExtractor-0.0.6.dist-info/top_level.txt
SNgramExtractor-0.0.6.dist-info/RECORD
