Metadata-Version: 2.1
Name: SNgramExtractor
Version: 0.0.6
Summary: Implementation of syntactic n-grams (sn-gram) extraction
Home-page: https://github.com/StatguyUser/SNgramExtractor
Author: StatguyUser
License: UNKNOWN
Download-URL: https://github.com/StatguyUser/SNgramExtractor.git
Platform: UNKNOWN
Requires-Dist: spacy
Requires-Dist: spacy[en_core_news_md]
